ebi_eva_common_pyutils/__init__.py
ebi_eva_common_pyutils/assembly_utils.py
ebi_eva_common_pyutils/biosamples_communicators.py
ebi_eva_common_pyutils/command_utils.py
ebi_eva_common_pyutils/common_utils.py
ebi_eva_common_pyutils/config.py
ebi_eva_common_pyutils/ena_utils.py
ebi_eva_common_pyutils/file_utils.py
ebi_eva_common_pyutils/logger.py
ebi_eva_common_pyutils/ncbi_utils.py
ebi_eva_common_pyutils/network_utils.py
ebi_eva_common_pyutils/assembly/__init__.py
ebi_eva_common_pyutils/assembly/assembly.py
ebi_eva_common_pyutils/contig_alias/__init__.py
ebi_eva_common_pyutils/contig_alias/contig_alias.py
ebi_eva_common_pyutils/reference/__init__.py
ebi_eva_common_pyutils/reference/assembly.py
ebi_eva_common_pyutils/reference/sequence.py
ebi_eva_common_pyutils/spreadsheet/__init__.py
ebi_eva_common_pyutils/spreadsheet/metadata_xlsx_utils.py
ebi_eva_common_pyutils/taxonomy/__init__.py
ebi_eva_common_pyutils/taxonomy/taxonomy.py
ebi_eva_common_pyutils/variation/__init__.py
ebi_eva_common_pyutils/variation/contig_utils.py
ebi_eva_common_pyutils-0.8.0.data/scripts/archive_directory.py
ebi_eva_internal_pyutils/__init__.py
ebi_eva_internal_pyutils/archive_directory.py
ebi_eva_internal_pyutils/config_utils.py
ebi_eva_internal_pyutils/metadata_utils.py
ebi_eva_internal_pyutils/mongo_utils.py
ebi_eva_internal_pyutils/pg_utils.py
ebi_eva_internal_pyutils/spring_properties.py
ebi_eva_internal_pyutils/mongodb/__init__.py
ebi_eva_internal_pyutils/mongodb/mongo_database.py
ebi_eva_common_pyutils-0.8.0.dist-info/LICENSE
ebi_eva_common_pyutils-0.8.0.dist-info/METADATA
ebi_eva_common_pyutils-0.8.0.dist-info/WHEEL
ebi_eva_common_pyutils-0.8.0.dist-info/top_level.txt
ebi_eva_common_pyutils-0.8.0.dist-info/RECORD
